rba/__init__.py
rba/_authors.py
rba/_version.py
rba/model.py
rba/cli/__init__.py
rba/cli/generate_rba_model.py
rba/cli/solve_rba_model.py
rba/core/__init__.py
rba/core/constraint_blocks.py
rba/core/constraint_matrix.py
rba/core/density.py
rba/core/enzymes.py
rba/core/functions.py
rba/core/metabolism.py
rba/core/parameter_vector.py
rba/core/parameters.py
rba/core/processes.py
rba/core/solver.py
rba/core/species.py
rba/core/targets.py
rba/prerba/__init__.py
rba/prerba/curation_data.py
rba/prerba/default_data.py
rba/prerba/default_processes.py
rba/prerba/default_targets.py
rba/prerba/enzyme.py
rba/prerba/fasta_parser.py
rba/prerba/macromolecule.py
rba/prerba/manual_annotation.py
rba/prerba/model_builder.py
rba/prerba/pipeline_parameters.py
rba/prerba/protein_data.py
rba/prerba/protein_export.py
rba/prerba/sbml_data.py
rba/prerba/uniprot_data.py
rba/prerba/uniprot_importer.py
rba/prerba/user_data.py
rba/prerba/user_machinery.py
rba/utils/__init__.py
rba/utils/efficiencies.py
rba/utils/results.py
rba/xml/__init__.py
rba/xml/common.py
rba/xml/density.py
rba/xml/enzymes.py
rba/xml/macromolecules.py
rba/xml/metabolism.py
rba/xml/parameters.py
rba/xml/processes.py
rba/xml/targets.py
rbapy-2.0.1.dist-info/LICENSE.txt
rbapy-2.0.1.dist-info/METADATA
rbapy-2.0.1.dist-info/WHEEL
rbapy-2.0.1.dist-info/entry_points.txt
rbapy-2.0.1.dist-info/top_level.txt
rbapy-2.0.1.dist-info/RECORD
