Metadata-Version: 2.1
Name: rbapy
Version: 2.0.1
Summary: Package for automated generation of bacterial Resource Balance Analysis (RBA) models and simulation of RBA models
Home-page: https://sysbioinra.github.io/RBApy/
Author: RBApy was conceived and implemented originally by INRAE (Stephan Fischer, Ana Bulovic, Anne Goelzer and Marc Dinh), and updated regularly by several contributors (Oliver Bodeit, Jonathan Karr, Michael Jahn)
Author-email: anne.goelzer@inra.fr
License: GPLv3
Keywords: metabolism,Resource Balance Analysis,molecular biology,cell biology,biochemistry,systems biology,computational biology,mathematical modeling,numerical simulation
Platform: UNKNOWN
Classifier: Development Status :: 3 - Alpha
Classifier: Intended Audience :: Science/Research
Classifier: Topic :: Scientific/Engineering
Classifier: Topic :: Scientific/Engineering :: Bio-Informatics
Classifier: License :: OSI Approved :: GNU General Public License v3 (GPLv3)
Classifier: Programming Language :: Python :: 2
Classifier: Programming Language :: Python :: 2.7
Classifier: Programming Language :: Python :: 3
Classifier: Programming Language :: Python :: 3.5
License-File: LICENSE.txt
Requires-Dist: biopython
Requires-Dist: lxml
Requires-Dist: numpy
Requires-Dist: pandas
Requires-Dist: python-libsbml
Requires-Dist: scipy
Requires-Dist: requests
Provides-Extra: cplex
Requires-Dist: cplex ; extra == 'cplex'
Provides-Extra: cplex_conv_opt
Requires-Dist: conv-opt[cplex] ; extra == 'cplex_conv_opt'
Provides-Extra: cplex_optlang
Requires-Dist: optlang ; extra == 'cplex_optlang'
Requires-Dist: cplex ; extra == 'cplex_optlang'
Provides-Extra: dev
Requires-Dist: check-manifest ; extra == 'dev'
Provides-Extra: glpk
Requires-Dist: glpk ; extra == 'glpk'
Provides-Extra: glpk_conv_opt
Requires-Dist: conv-opt ; extra == 'glpk_conv_opt'
Provides-Extra: glpk_optlang
Requires-Dist: optlang ; extra == 'glpk_optlang'
Provides-Extra: gurobi
Requires-Dist: gurobipy ; extra == 'gurobi'
Provides-Extra: gurobi_conv_opt
Requires-Dist: conv-opt[gurobi] ; extra == 'gurobi_conv_opt'
Provides-Extra: gurobi_optlang
Requires-Dist: optlang ; extra == 'gurobi_optlang'
Requires-Dist: gurobipy ; extra == 'gurobi_optlang'
Provides-Extra: swiglpk
Requires-Dist: swiglpk ; extra == 'swiglpk'
Provides-Extra: test
Requires-Dist: pytest ; extra == 'test'
Requires-Dist: pytest-cov ; extra == 'test'
Requires-Dist: coverage ; extra == 'test'
